MIDP/__init__.py
MIDP/utils.py
MIDP-0.0.4.dist-info/LICENSE
MIDP-0.0.4.dist-info/METADATA
MIDP-0.0.4.dist-info/WHEEL
MIDP-0.0.4.dist-info/top_level.txt
MIDP-0.0.4.dist-info/RECORD
