Metadata-Version: 2.1
Name: MIDP
Version: 0.0.4
Summary: Medical Image Development Packages
Home-page: https://github.com/SaberPRC/MIA-Tools
Author: Jiameng Liu
Author-email: JiamengLiu.PRC@gmail.com
Classifier: Programming Language :: Python :: 3
Classifier: License :: OSI Approved :: MIT License
Classifier: Operating System :: OS Independent
License-File: LICENSE
Requires-Dist: antspyx
Requires-Dist: numpy
Requires-Dist: SimpleITK
Requires-Dist: scikit-image
